{"v": 1, "voz": "pt-BR-FranciscaNeural", "blocks": [{"t": 0.1, "s": "Capítulo 4 - Armas Longas (Rifle, Fuzil,"}, {"t": 4.987, "s": "Índice"}, {"t": 5.812, "s": "4 Estudo das armas de fogo longas"}, {"t": 8.4, "s": "As armas longas, como o próprio termo di"}, {"t": 42.65, "s": "4.1 Estudo particular do rifle"}, {"t": 45.45, "s": "O termo rifle deriva do inglês rifled, q"}, {"t": 105.95, "s": "Figura 37 – nomenclatura das peças exter"}, {"t": 111.75, "s": "4.2 Estudo particular do fuzil"}, {"t": 114.662, "s": "Os fuzis são armas de fogo longas, poden"}, {"t": 148.275, "s": "Figura 38 – Fuzil de assalto leve - FAL "}, {"t": 153.65, "s": "4.3 Estudo particular da carabina"}, {"t": 156.662, "s": "Carabinas são armas de fogo longas, port"}, {"t": 239.613, "s": "Figura 39 – Nomenclatura das peças exter"}, {"t": 245.588, "s": "4.4 Estudo particular do mosquetão"}, {"t": 249.436, "s": "Mosquetões são armas de fogo longas, de "}, {"t": 320.336, "s": "Figura 40 – Mosquetão Mauser modelo 1898"}, {"t": 326.611, "s": "4.5 Estudo particular da espingarda"}, {"t": 329.798, "s": "A principal característica das espingard"}, {"t": 390.849, "s": "Figura 41 – Nomenclatura das peças exter"}, {"t": 396.786, "s": "Jost)."}, {"t": 397.586, "s": "Figura 42 – Nomenclatura das peças exter"}, {"t": 403.423, "s": "4.5.1 Cartucho de munição para espingard"}, {"t": 407.236, "s": "Quando comparados com cartuchos de muniç"}, {"t": 456.486, "s": "Figura 43 – Esquema de um cartucho de fo"}, {"t": 461.261, "s": "(Ilustração: Marcelo Jost)."}, {"t": 463.373, "s": "4.5.2 O estojo de munição para espingard"}, {"t": 468.172, "s": "O estojo de cartuchos de espingardas é, "}, {"t": 510.709, "s": "4.5.3 Os projéteis de munição para espin"}, {"t": 514.985, "s": "Os cartuchos para espingardas são, de mo"}, {"t": 533.21, "s": "Figura 44 – Especificações de balins de "}, {"t": 539.972, "s": "Companhia Brasileira de Cartuchos – Font"}, {"t": 576.697, "s": "4.5.4 Calibre em armas de alma lisa – ca"}, {"t": 582.135, "s": "O calibre real em armas de alma lisa é a"}, {"t": 654.522, "s": ": um asterisco, indicando choque Full;"}, {"t": 656.872, "s": ": dois asteriscos, indicando choque Modi"}, {"t": 659.822, "s": ": três asteriscos, indicando choque Impr"}, {"t": 663.11, "s": "Figura 45 – Ilustração esquemática do ch"}, {"t": 669.635, "s": "4.5.5 Calibre em armas de alma lisa – ca"}, {"t": 674.622, "s": "O calibre nominal em armas de alma lisa "}, {"t": 721.96, "s": "Figura 46 – Cálculo do calibre nominal p"}, {"t": 728.548, "s": "Desse modo, o calibre real, que correspo"}, {"t": 749.398, "s": "Tabela 2 – Calibre nominal e calibre rea"}, {"t": 752.523, "s": "Calibre Nominal — Calibre Real (mm)"}, {"t": 755.336, "s": "12 — 18,5"}, {"t": 757.598, "s": "16 — 16,2"}, {"t": 760.048, "s": "20 — 15,9"}, {"t": 762.148, "s": "Calibre Nominal — Calibre Real (mm)"}, {"t": 764.961, "s": "24 — 14,3"}, {"t": 767.723, "s": "28 — 13,0"}, {"t": 769.998, "s": "32 — 12,2"}, {"t": 772.298, "s": "36 — 10,2"}, {"t": 774.548, "s": "Não obstante o exemplo acima, dizer que "}]}